LICENSE
py_patterns/__init__.py
py_patterns/adapters/__init__.py
py_patterns/adapters/adapter.py
py_patterns/base.py
py_patterns_util-0.1.1.dist-info/LICENSE
py_patterns_util-0.1.1.dist-info/WHEEL
py_patterns_util-0.1.1.dist-info/METADATA
py_patterns_util-0.1.1.dist-info/RECORD
