Metadata-Version: 2.1
Name: py-patterns-util
Version: 0.1.1
Summary: A util library for common patterns in python.
Home-page: https://github.com/priyanshujain/py-patterns
License: MIT
Keywords: python,design-patterns,adapters
Author: Priyanshu Jain
Author-email: ipriyanshujain@gmail.com
Requires-Python: >=3.9,<4.0
Classifier: License :: OSI Approved :: MIT License
Classifier: Programming Language :: Python :: 3
Classifier: Programming Language :: Python :: 3.9
Requires-Dist: absl-py (>=1.1.0,<2.0.0)
Project-URL: Repository, https://github.com/priyanshujain/py-patterns
